CHANGES.rst
LICENSE
MANIFEST.in
README.rst
setup.py
xtraceback/__init__.py
xtraceback/defaults.py
xtraceback/formatting.py
xtraceback/lexer.py
xtraceback/loggingcompat.py
xtraceback/moduleshim.py
xtraceback/nosextraceback.py
xtraceback/pycompat.py
xtraceback/tracebackcompat.py
xtraceback/xtraceback.py
xtraceback/xtracebackexc.py
xtraceback/xtracebackframe.py
xtraceback/xtracebackoptions.py
xtraceback.egg-info/PKG-INFO
xtraceback.egg-info/SOURCES.txt
xtraceback.egg-info/dependency_links.txt
xtraceback.egg-info/requires.txt
xtraceback.egg-info/top_level.txt